hdl_projects/counter.vhd
library ieee;
use ieee.std_logic_1164.all;
use ieee.numeric_std.all;
-- 8-bit synchronous counter
entity counter is
    port (
        clk : in std_logic;
        rst : in std_logic;
        q : out std_logic_vector(7 downto 0)
    );
end counter;

architecture Behavioral of counter is
    signal cnt : unsigned(7 downto 0);
begin
    process(clk, rst)
    begin
        if rst = '1' then
            cnt <= (others => '0');
        elsif rising_edge(clk) then
            cnt <= cnt + 1;
        end if;
        q <= std_logic_vector(cnt);
    end process;
end Behavioral;

hdl_projects/tb_counter.vhd
library ieee;
use ieee.std_logic_1164.all;
use ieee.numeric_std.all;
entity tb_counter is end;
architecture test of tb_counter is
    signal clk, rst : std_logic;
    signal q : std_logic_vector(7 downto 0);
begin
    uut: entity work.counter port map(clk=>clk, rst=>rst, q=>q);
    process
    begin
        clk <= '0'; rst <= '1'; wait for 1 ns;
        rst <= '0';
        for i in 0 to 3 loop
            clk <= '1'; wait for 1 ns;
            clk <= '0'; wait for 1 ns;
            report "q=" & integer'image(to_integer(unsigned(q)));
        end loop;
        wait;
    end process;
end;

tb_counter.vcd
$date
  Mon Aug 11 15:58:14 2025
$end
$version
  GHDL v0
$end
$timescale
  1 fs
$end
$scope module standard $end
$upscope $end
$scope module std_logic_1164 $end
$upscope $end
$scope module numeric_std $end
$upscope $end
$scope module tb_counter $end
$var reg 1 ! clk $end
$var reg 1 " rst $end
$var reg 8 # q[7:0] $end
$scope module uut $end
$var reg 1 $ clk $end
$var reg 1 % rst $end
$var reg 8 & q[7:0] $end
$var reg 8 ' cnt[7:0] $end
$upscope $end
$upscope $end
$enddefinitions $end
#0
0!
1"
bUUUUUUUU #
0$
1%
bUUUUUUUU &
b00000000 '
#1000000
1!
0"
b00000000 #
1$
0%
b00000000 &
b00000001 '
#2000000
0!
b00000001 #
0$
b00000001 &
#3000000
1!
1$
b00000010 '
#4000000
0!
b00000010 #
0$
b00000010 &
#5000000
1!
1$
b00000011 '
#6000000
0!
b00000011 #
0$
b00000011 &
#7000000
1!
1$
b00000100 '
#8000000
0!
b00000100 #
0$
b00000100 &
